tg/Bot.py
tg/Content.py
tg/Response.py
tg/__init__.py
tgbf-0.0.3.dist-info/LICENSE
tgbf-0.0.3.dist-info/METADATA
tgbf-0.0.3.dist-info/WHEEL
tgbf-0.0.3.dist-info/top_level.txt
tgbf-0.0.3.dist-info/RECORD
