Metadata-Version: 2.1
Name: tgbf
Version: 0.0.3
Summary: Telegram Bot Framework
Home-page: https://github.com/WiGeeky/TGBotFramework
Author: Mike
Author-email: mike@mikey.ir
License: UNKNOWN
Platform: UNKNOWN
Classifier: Programming Language :: Python :: 3
Classifier: License :: OSI Approved :: MIT License
Classifier: Operating System :: OS Independent
Requires-Python: >=3.7
